blackhc/implicit_lambda/__init__.py
blackhc/implicit_lambda/args_resolver.py
blackhc/implicit_lambda/builtins.py
blackhc/implicit_lambda/functools.py
blackhc/implicit_lambda/itertools.py
blackhc/implicit_lambda/details/codegen.py
blackhc/implicit_lambda/details/collect_args.py
blackhc/implicit_lambda/details/expression.py
blackhc/implicit_lambda/details/glue.py
blackhc/implicit_lambda/details/interpret.py
blackhc/implicit_lambda/details/lambda_dsl.py
blackhc/implicit_lambda/details/placeholders.py
blackhc/implicit_lambda/tests/__init__.py
blackhc/implicit_lambda/tests/test_args_resolver.py
blackhc/implicit_lambda/tests/test_auto_lambdas.py
blackhc/implicit_lambda/tests/test_codegen.py
blackhc/implicit_lambda/tests/test_implicit_lambda.py
blackhc/implicit_lambda/tests/test_ops.py
blackhc/implicit_lambda/tests/test_performance.py
blackhc/implicit_lambda/tests/test_placeholders.py
blackhc/implicit_lambda/tests/test_special_ops.py
blackhc.implicit_lambda-0.4.0.dist-info/LICENSE
blackhc.implicit_lambda-0.4.0.dist-info/METADATA
blackhc.implicit_lambda-0.4.0.dist-info/WHEEL
blackhc.implicit_lambda-0.4.0.dist-info/top_level.txt
blackhc.implicit_lambda-0.4.0.dist-info/RECORD
