Metadata-Version: 2.1
Name: blackhc.implicit-lambda
Version: 0.4.0
Summary: Implicit lambdas with placeholder notation and code generation
Home-page: https://github.com/blackhc/implicit_lambda
Author: Andreas @blackhc Kirsch
Author-email: blackhc+implicit_lambda@gmail.com
License: MIT
Keywords: tools lambda placeholder
Platform: UNKNOWN
Classifier: Development Status :: 3 - Alpha
Classifier: Intended Audience :: Developers
Classifier: Intended Audience :: Science/Research
Classifier: Topic :: Software Development :: Libraries :: Python Modules
Classifier: License :: OSI Approved :: MIT License
Classifier: Programming Language :: Python :: 3.7
Provides-Extra: dev
Requires-Dist: check-manifest ; extra == 'dev'
Provides-Extra: test
Requires-Dist: coverage ; extra == 'test'
Requires-Dist: codecov ; extra == 'test'
Requires-Dist: pytest ; extra == 'test'
Requires-Dist: pytest-benchmark ; extra == 'test'
Requires-Dist: pytest-cov ; extra == 'test'
Requires-Dist: hypothesis ; extra == 'test'
